{"store":{"name":"Luxe Joyería","description_es":"Exclusividad y Brillo en cada detalle","description_en":"Exclusivity and Brilliance in every detail","whatsapp":"+1234567890","address":"Calle Real 123, Madrid, España","location_url":"https://goo.gl/maps/example","owner_contact":"+1234567891","currency":"USD","announcement":"mi anuncio 🪧"},"categories":[{"id":"anillos","name_es":"Anillos","name_en":"Rings","icon":"💍"},{"id":"collares","name_es":"Collares","name_en":"Necklaces","icon":"📿"},{"id":"pulseras","name_es":"Pulseras","name_en":"Bracelets","icon":"⌚"},{"id":"pendientes","name_es":"Pendientes","name_en":"Earrings","icon":"✨"},{"id":"relojes","name_es":"Relojes","name_en":"Watches","icon":"🕒"}],"products":[{"id":1,"category":"anillos","name_es":"Anillo de Diamante Eterno","name_en":"Eternal Diamond Ring","description_es":"","description_en":"","price":1200.0,"stock":0,"is_offer":false,"is_deal_of_day":false,"image":"images/anillo1.webp"},{"id":2,"category":"anillos","name_es":"Alianza de Oro Rosa","name_en":"Rose Gold Wedding Band","description_es":"","description_en":"","price":2500.0,"stock":0,"is_offer":true,"is_deal_of_day":true,"image":"images/anillo2.webp","discount_price":2100.0},{"id":3,"category":"collares","name_es":"Collar de Perlas Australianas","name_en":"Australian Pearl Necklace","description_es":"","description_en":"","price":3800.0,"stock":0,"is_offer":false,"is_deal_of_day":false,"image":"images/collar1.webp"},{"id":4,"category":"collares","name_es":"Gargantilla de Zafiro","name_en":"Sapphire Choker","description_es":"","description_en":"","price":1500.0,"stock":0,"is_offer":false,"is_deal_of_day":false,"image":"images/collar2.webp"},{"id":5,"category":"pulseras","name_es":"Pulsera Tennis","name_en":"Tennis Bracelet","description_es":"","description_en":"","price":950.0,"stock":0,"is_offer":true,"is_deal_of_day":true,"image":"images/pulsera1.webp","discount_price":760.0},{"id":6,"category":"pendientes","name_es":"Aros Solitarios","name_en":"Solitary Hoop Earrings","description_es":"","description_en":"","price":600.0,"stock":0,"is_offer":false,"is_deal_of_day":false,"image":"images/pendientes1.webp"},{"id":7,"category":"relojes","name_es":"Reloj Chrono Elite","name_en":"Elite Chrono Watch","description_es":"","description_en":"","price":5000.0,"stock":0,"is_offer":false,"is_deal_of_day":false,"image":"images/reloj1.webp"},{"id":8,"category":"relojes","name_es":"Lujo Edición Oro","name_en":"Gold Edition Luxury","description_es":"","description_en":"","price":12000.0,"stock":0,"is_offer":true,"is_deal_of_day":false,"image":"images/reloj2.webp","discount_price":10800.0}]}